{
	"configurations" : 
	[
		{
			"directories" : 
			[
				{
					"build" : ".",
					"childIndexes" : 
					[
						1
					],
					"hasInstallRule" : true,
					"jsonFile" : "directory-.-Release-0dc699f8b952ba0466fc.json",
					"minimumCMakeVersion" : 
					{
						"string" : "3.15"
					},
					"projectIndex" : 0,
					"source" : ".",
					"targetIndexes" : 
					[
						0,
						1,
						4,
						5,
						6,
						7,
						8,
						9,
						11
					]
				},
				{
					"build" : "test",
					"childIndexes" : 
					[
						2
					],
					"jsonFile" : "directory-test-Release-451c0598f41488bb20b9.json",
					"minimumCMakeVersion" : 
					{
						"string" : "3.15"
					},
					"parentIndex" : 0,
					"projectIndex" : 0,
					"source" : "test",
					"targetIndexes" : 
					[
						10
					]
				},
				{
					"build" : "gtest",
					"jsonFile" : "directory-gtest-Release-0908a8c91ddba5d6c989.json",
					"minimumCMakeVersion" : 
					{
						"string" : "3.8"
					},
					"parentIndex" : 1,
					"projectIndex" : 1,
					"source" : "/opt/ros/jazzy/src/gtest_vendor",
					"targetIndexes" : 
					[
						2,
						3
					]
				}
			],
			"name" : "Release",
			"projects" : 
			[
				{
					"childIndexes" : 
					[
						1
					],
					"directoryIndexes" : 
					[
						0,
						1
					],
					"name" : "nav2_behaviors",
					"targetIndexes" : 
					[
						0,
						1,
						4,
						5,
						6,
						7,
						8,
						9,
						10,
						11
					]
				},
				{
					"directoryIndexes" : 
					[
						2
					],
					"name" : "gtest",
					"parentIndex" : 0,
					"targetIndexes" : 
					[
						2,
						3
					]
				}
			],
			"targets" : 
			[
				{
					"directoryIndex" : 0,
					"id" : "behavior_server::@6890427a1f51a3e7e1df",
					"jsonFile" : "target-behavior_server-Release-c1615f67ebf59eb2ba1e.json",
					"name" : "behavior_server",
					"projectIndex" : 0
				},
				{
					"directoryIndex" : 0,
					"id" : "behavior_server_core::@6890427a1f51a3e7e1df",
					"jsonFile" : "target-behavior_server_core-Release-408427034faa3e068f6a.json",
					"name" : "behavior_server_core",
					"projectIndex" : 0
				},
				{
					"directoryIndex" : 2,
					"id" : "gtest::@0af4add9fe94340e763e",
					"jsonFile" : "target-gtest-Release-666a8a1f8e1f712f2d5e.json",
					"name" : "gtest",
					"projectIndex" : 1
				},
				{
					"directoryIndex" : 2,
					"id" : "gtest_main::@0af4add9fe94340e763e",
					"jsonFile" : "target-gtest_main-Release-8ad64d4b79a2e799f54e.json",
					"name" : "gtest_main",
					"projectIndex" : 1
				},
				{
					"directoryIndex" : 0,
					"id" : "nav2_assisted_teleop_behavior::@6890427a1f51a3e7e1df",
					"jsonFile" : "target-nav2_assisted_teleop_behavior-Release-bc56e9716a8fef5393e1.json",
					"name" : "nav2_assisted_teleop_behavior",
					"projectIndex" : 0
				},
				{
					"directoryIndex" : 0,
					"id" : "nav2_back_up_behavior::@6890427a1f51a3e7e1df",
					"jsonFile" : "target-nav2_back_up_behavior-Release-1e0afc67061e97948f4d.json",
					"name" : "nav2_back_up_behavior",
					"projectIndex" : 0
				},
				{
					"directoryIndex" : 0,
					"id" : "nav2_behaviors_uninstall::@6890427a1f51a3e7e1df",
					"jsonFile" : "target-nav2_behaviors_uninstall-Release-85e8c05b28263dc37e12.json",
					"name" : "nav2_behaviors_uninstall",
					"projectIndex" : 0
				},
				{
					"directoryIndex" : 0,
					"id" : "nav2_drive_on_heading_behavior::@6890427a1f51a3e7e1df",
					"jsonFile" : "target-nav2_drive_on_heading_behavior-Release-7292af973fb0dc1c407a.json",
					"name" : "nav2_drive_on_heading_behavior",
					"projectIndex" : 0
				},
				{
					"directoryIndex" : 0,
					"id" : "nav2_spin_behavior::@6890427a1f51a3e7e1df",
					"jsonFile" : "target-nav2_spin_behavior-Release-ffc27f9a741fac3a8dde.json",
					"name" : "nav2_spin_behavior",
					"projectIndex" : 0
				},
				{
					"directoryIndex" : 0,
					"id" : "nav2_wait_behavior::@6890427a1f51a3e7e1df",
					"jsonFile" : "target-nav2_wait_behavior-Release-2e6a1b6ab86c50332eb5.json",
					"name" : "nav2_wait_behavior",
					"projectIndex" : 0
				},
				{
					"directoryIndex" : 1,
					"id" : "test_behaviors::@36f028580bb02cc8272a",
					"jsonFile" : "target-test_behaviors-Release-45a199e843012407005c.json",
					"name" : "test_behaviors",
					"projectIndex" : 0
				},
				{
					"directoryIndex" : 0,
					"id" : "uninstall::@6890427a1f51a3e7e1df",
					"jsonFile" : "target-uninstall-Release-2c902e236d2b44e7c478.json",
					"name" : "uninstall",
					"projectIndex" : 0
				}
			]
		}
	],
	"kind" : "codemodel",
	"paths" : 
	{
		"build" : "/home/ranas/turtlebot4_ws/src/build/nav2_behaviors",
		"source" : "/home/ranas/turtlebot4_ws/src/navigation2/nav2_behaviors"
	},
	"version" : 
	{
		"major" : 2,
		"minor" : 6
	}
}
